LICENSE
repotoire-0.1.3.dist-info/METADATA
repotoire-0.1.3.dist-info/WHEEL
repotoire-0.1.3.dist-info/entry_points.txt
repotoire-0.1.3.dist-info/licenses/LICENSE
repotoire/__init__.py
repotoire/ai/__init__.py
repotoire/ai/contextual.py
repotoire/ai/embeddings.py
repotoire/ai/hybrid.py
repotoire/ai/llm.py
repotoire/ai/reranker.py
repotoire/ai/retrieval.py
repotoire/ai/spacy_clue_generator.py
repotoire/api/__init__.py
repotoire/api/app.py
repotoire/api/auth/__init__.py
repotoire/api/auth/clerk.py
repotoire/api/auth/state_store.py
repotoire/api/docs/__init__.py
repotoire/api/docs/webhooks.py
repotoire/api/middleware/__init__.py
repotoire/api/middleware/usage.py
repotoire/api/models.py
repotoire/api/routes/__init__.py
repotoire/api/routes/account.py
repotoire/api/routes/admin/__init__.py
repotoire/api/routes/admin/overrides.py
repotoire/api/routes/analysis.py
repotoire/api/routes/analytics.py
repotoire/api/routes/audit.py
repotoire/api/routes/billing.py
repotoire/api/routes/cli_auth.py
repotoire/api/routes/code.py
repotoire/api/routes/customer_webhooks.py
repotoire/api/routes/findings.py
repotoire/api/routes/fixes.py
repotoire/api/routes/github.py
repotoire/api/routes/historical.py
repotoire/api/routes/notifications.py
repotoire/api/routes/organizations.py
repotoire/api/routes/sandbox.py
repotoire/api/routes/team.py
repotoire/api/routes/usage.py
repotoire/api/routes/webhooks.py
repotoire/api/schemas/__init__.py
repotoire/api/schemas/fix.py
repotoire/api/schemas/quota_override.py
repotoire/api/services/__init__.py
repotoire/api/services/asset_packager.py
repotoire/api/services/asset_storage.py
repotoire/api/services/asset_validator.py
repotoire/api/services/billing.py
repotoire/api/services/changelog.py
repotoire/api/services/cloud_storage.py
repotoire/api/services/encryption.py
repotoire/api/services/gdpr.py
repotoire/api/services/github.py
repotoire/api/services/marketplace.py
repotoire/api/services/notifications.py
repotoire/api/services/status_emails.py
repotoire/api/services/stripe_service.py
repotoire/api/shared/__init__.py
repotoire/api/shared/auth/__init__.py
repotoire/api/shared/auth/clerk.py
repotoire-0.1.3.dist-info/RECORD
