Metadata-Version: 2.4
Name: repotoire
Version: 0.1.3
Classifier: Development Status :: 3 - Alpha
Classifier: Intended Audience :: Developers
Classifier: Programming Language :: Python :: 3
Classifier: Programming Language :: Python :: 3.10
Classifier: Programming Language :: Python :: 3.11
Classifier: Programming Language :: Python :: 3.12
Classifier: Programming Language :: Python :: 3.13
Classifier: Topic :: Software Development :: Quality Assurance
Requires-Dist: falkordb>=1.0.0
Requires-Dist: openai>=1.0.0
Requires-Dist: spacy>=3.7.0
Requires-Dist: click>=8.1.0
Requires-Dist: rich>=13.0.0
Requires-Dist: pydantic>=2.0.0
Requires-Dist: networkx>=3.2.0
Requires-Dist: jinja2>=3.1.0
Requires-Dist: detect-secrets>=1.4.0
Requires-Dist: gitpython>=3.1.40
Requires-Dist: neo4j-graphrag>=1.10.1
Requires-Dist: fastapi>=0.121.3
Requires-Dist: uvicorn>=0.38.0
Requires-Dist: mcp>=1.22.0
Requires-Dist: python-dotenv>=1.2.1
Requires-Dist: clerk-backend-api>=4.2.0
Requires-Dist: httpx>=0.27.0
Requires-Dist: pyjwt[crypto]>=2.8.0
Requires-Dist: cryptography>=41.0.0
Requires-Dist: svix>=1.0.0
Requires-Dist: keyring>=24.0.0
Requires-Dist: sqlalchemy>=2.0.0
Requires-Dist: alembic>=1.13.0
Requires-Dist: psycopg2-binary>=2.9.9
Requires-Dist: asyncpg>=0.29.0
Requires-Dist: stripe>=7.0.0
Requires-Dist: celery>=5.3.0
Requires-Dist: redis>=5.0.0
Requires-Dist: structlog>=24.0.0
Requires-Dist: sentry-sdk[fastapi,celery,sqlalchemy]>=2.0.0
Requires-Dist: resend>=0.5.0
Requires-Dist: aioboto3>=13.0.0
Requires-Dist: email-validator>=2.0.0
Requires-Dist: python-slugify>=8.0.0
Requires-Dist: bleach>=6.0.0
Requires-Dist: slowapi>=0.1.9
Requires-Dist: uv-secure>=0.15.0
Requires-Dist: datasets>=2.14.0
Requires-Dist: sentence-transformers>=2.2.0
Requires-Dist: accelerate>=0.26.0
Requires-Dist: mypy>=1.7.0
Requires-Dist: pylint>=3.0.0
Requires-Dist: bandit>=1.7.0
Requires-Dist: radon>=6.0.0
Requires-Dist: vulture>=2.0.0
Requires-Dist: semgrep>=1.0.0
Requires-Dist: pytest>=7.4.0 ; extra == 'dev'
Requires-Dist: pytest-cov>=4.1.0 ; extra == 'dev'
Requires-Dist: pytest-xdist>=3.5.0 ; extra == 'dev'
Requires-Dist: pytest-benchmark>=4.0.0 ; extra == 'dev'
Requires-Dist: pytest-asyncio>=0.23.0 ; extra == 'dev'
Requires-Dist: pytest-timeout>=2.2.0 ; extra == 'dev'
Requires-Dist: hypothesis>=6.100.0 ; extra == 'dev'
Requires-Dist: factory-boy>=3.3.0 ; extra == 'dev'
Requires-Dist: httpx>=0.27.0 ; extra == 'dev'
Requires-Dist: black>=23.0.0 ; extra == 'dev'
Requires-Dist: ruff>=0.1.0 ; extra == 'dev'
Requires-Dist: mypy>=1.7.0 ; extra == 'dev'
Requires-Dist: pyyaml>=6.0 ; extra == 'dev'
Requires-Dist: tomli>=2.0.0 ; extra == 'dev'
Requires-Dist: tenacity>=8.2.0 ; extra == 'dev'
Requires-Dist: redis>=5.0.0 ; extra == 'dev'
Requires-Dist: pyyaml>=6.0 ; extra == 'config'
Requires-Dist: tomli>=2.0.0 ; python_full_version < '3.11' and extra == 'config'
Requires-Dist: graphdatascience>=1.9.0 ; extra == 'gds'
Requires-Dist: tree-sitter>=0.20.0 ; extra == 'all-languages'
Requires-Dist: tree-sitter-python>=0.20.0 ; extra == 'all-languages'
Requires-Dist: tree-sitter-javascript>=0.20.0 ; extra == 'all-languages'
Requires-Dist: tree-sitter-typescript>=0.20.0 ; extra == 'all-languages'
Requires-Dist: psycopg2-binary>=2.9.9 ; extra == 'timescale'
Requires-Dist: graphiti-core>=0.24.1 ; extra == 'graphiti'
Requires-Dist: pip-audit>=2.6.0 ; extra == 'security'
Requires-Dist: cyclonedx-bom>=4.0.0 ; extra == 'security'
Requires-Dist: prometheus-client>=0.19.0 ; extra == 'observability'
Requires-Dist: opentelemetry-api>=1.20.0 ; extra == 'observability'
Requires-Dist: opentelemetry-sdk>=1.20.0 ; extra == 'observability'
Requires-Dist: opentelemetry-exporter-otlp>=1.20.0 ; extra == 'observability'
Requires-Dist: sentry-sdk[fastapi,celery,sqlalchemy]>=2.0.0 ; extra == 'observability'
Requires-Dist: questionary>=2.0.0 ; extra == 'ml'
Requires-Dist: scikit-learn>=1.3.0 ; extra == 'ml'
Requires-Dist: joblib>=1.3.0 ; extra == 'ml'
Requires-Dist: torch>=2.5.0,<2.9.0 ; extra == 'ml'
Requires-Dist: torch-geometric>=2.6.0 ; extra == 'ml'
Requires-Dist: gensim>=4.3.0 ; extra == 'ml'
Requires-Dist: e2b-code-interpreter>=1.0.0 ; extra == 'sandbox'
Requires-Dist: voyageai>=0.3.0 ; extra == 'voyage'
Requires-Dist: anthropic>=0.40.0 ; extra == 'anthropic'
Provides-Extra: dev
Provides-Extra: config
Provides-Extra: gds
Provides-Extra: all-languages
Provides-Extra: timescale
Provides-Extra: graphiti
Provides-Extra: security
Provides-Extra: local-embeddings
Provides-Extra: observability
Provides-Extra: ml
Provides-Extra: sandbox
Provides-Extra: voyage
Provides-Extra: anthropic
License-File: LICENSE
Summary: Graph-Powered Code Health Platform
Keywords: code-analysis,knowledge-graph,technical-debt,neo4j,static-analysis
Author: Repotoire Team
License-Expression: MIT
Requires-Python: >=3.10
Project-URL: Homepage, https://github.com/yourusername/repotoire
Project-URL: Documentation, https://repotoire.readthedocs.io
Project-URL: Repository, https://github.com/yourusername/repotoire
Project-URL: Issues, https://github.com/yourusername/repotoire/issues
